CHANGELOG.txt
LICENSE.txt
MANIFEST.in
README.rst
setup.cfg
setup.py
PyIntervalTree.egg-info/PKG-INFO
PyIntervalTree.egg-info/SOURCES.txt
PyIntervalTree.egg-info/dependency_links.txt
PyIntervalTree.egg-info/requires.txt
PyIntervalTree.egg-info/top_level.txt
PyIntervalTree.egg-info/zip-safe
intervaltree/__init__.py
intervaltree/interval.py
intervaltree/intervaltree.py
intervaltree/node.py
intervaltree/bio/__init__.py