Metadata-Version: 1.1
Name: PyIntervalTree
Version: 0.5
Summary: Mutable, self-balancing interval tree
Home-page: https://github.com/konstantint/PyIntervalTree
Author: Chaim-Leib Halbert, Konstantin Tretyakov
Author-email: kt@ut.ee
License: LGPL
Keywords: interval-tree data-structure intervals tree
Platform: UNKNOWN
Classifier: Development Status :: 7 - Inactive
Classifier: Programming Language :: Python
Classifier: Intended Audience :: Science/Research
Classifier: License :: OSI Approved :: GNU Lesser General Public License v3 (LGPLv3)
Classifier: Topic :: Scientific/Engineering :: Bio-Informatics
Classifier: Topic :: Software Development :: Libraries
